gpt_translator/__init__.py
gpt_translator/main.py
gpt_translator_lc-0.0.1.dist-info/METADATA
gpt_translator_lc-0.0.1.dist-info/WHEEL
gpt_translator_lc-0.0.1.dist-info/entry_points.txt
gpt_translator_lc-0.0.1.dist-info/top_level.txt
gpt_translator_lc-0.0.1.dist-info/RECORD
