Metadata-Version: 2.1
Name: gpt-translator-lc
Version: 0.0.1
Summary: None
Home-page: https://github.com/zc277584121/GPTTranslator
Author: zc
Author-email: 277584121@qq.com
Requires-Dist: langchain
Requires-Dist: langchain-community
Requires-Dist: langchain-core
Requires-Dist: langchain-openai
Requires-Dist: tqdm
Requires-Dist: argparse
